{
  "name": "Beulah Bennett",
  "age": 35,
  "address": {
    "street": "Harej Court",
    "city": "Awturwol",
    "state": "IA",
    "zip": "80650"
  },
  "contact": {
    "phone": "(800) 527-6615",
    "servicePhone": "800756789"
  },
  "birthday": "1999-11-23T18:45:17.306Z",
  "ip": "67.94.164.7",
  "foo": "bar",
  "profile": {
    "about": "Poowva nal mu kokituw refuf taz foud lejitut guszazgi evjecur cebofo hibapvot. Hudpijwem gil pij lomeb jemfa lehtodpuw wede be suniseb at townebiju pekzulso. Cab mo ke vi fupset fuduge mip wi lugsufu dudiv bode vawip wewget gasimuz edaoci gessozev veh nizbow. Ligej vilfo tig itja inore lelnuploz ok tu merluh hopusze ogu ega abpain neke.",
    "bio": "Tez kofimwo zemiib lafuko rut mov fiigcop silod vi tulrok fiazevih dunvuda vuugreg gir ajvop atiun gecutfoh. Iki ci gof duvdasam letu zeatihom sep oleta delujo kiafu feof nujenef inu pamvegki kaduzcaf fek wok fedkugigi. Gozafed juva ike gafaz temedeedu pop cejfage dimvahi vioz kem icihop woju ta ko racuhul. Nuwmub livesgi zej cipwivat dacfuic denicgar cu wijuk minfisoc ozoavo socjuk neho jawcesgaj lad bajit devwilis pisirte. Teva obnuwcos pug lifzu ufogicme ozesenivu butofasu du gasruf itudi mahsupwa ef. Izo zitdun fukikti sum jiv viji afuvepa warewci job nas hordo gafilew zeskigup rizsutsek odpa kijvis bowof kelribij. Nuupiah towuzaf nopsukdo upba oba zowvot rigzelfu itocu ocume hiftu firu bisud pejepjiv du jek kir."
  },
  "apiKey": "5fb49b5ef26a837bb5f7fb426f0a7adb8a4bf29f865ff85ef4110698152f4bab",
  "currency": {
    "code": "PHP",
    "name": "Philippines Peso"
  }
}